dns_traffic_analysis/__init__.py
dns_traffic_analysis/bin/__init__.py
dns_traffic_analysis/bin/dns-packet-parser.py
dns_traffic_analysis/bin/dns-pkt-rpt.py
dns_traffic_analysis/bin/dns-splitter.py
dns_traffic_analysis/bin/find-dns-server.py
dns_traffic_analysis/bin/traffic-analysis.py
dns_traffic_analysis-0.1.0.dist-info/METADATA
dns_traffic_analysis-0.1.0.dist-info/WHEEL
dns_traffic_analysis-0.1.0.dist-info/licenses/LICENSE
dns_traffic_analysis-0.1.0.dist-info/RECORD
