Metadata-Version: 2.4
Name: dns-traffic-analysis
Version: 0.1.0
Summary: Tools for analyzing PCAP files to identify DNS queries with high latency.
License: BSD 2-Clause License
License-File: LICENSE
Keywords: dns,pcap,troubleshooting,diagnostic,network
Author: Michael Ragusa
Author-email: mragusa@infoblox.com
Requires-Python: >=3.12,<4.0
Classifier: License :: Other/Proprietary License
Classifier: Programming Language :: Python :: 3
Classifier: Programming Language :: Python :: 3.12
Classifier: Programming Language :: Python :: 3.13
Classifier: Programming Language :: Python :: 3.14
Requires-Dist: anyio (==4.10.0)
Requires-Dist: build (==1.3.0)
Requires-Dist: cachecontrol (==0.14.3)
Requires-Dist: certifi (==2025.8.3)
Requires-Dist: cffi (==2.0.0)
Requires-Dist: charset-normalizer (==3.4.3)
Requires-Dist: cleo (==2.1.0)
Requires-Dist: crashtest (==0.4.1)
Requires-Dist: distlib (==0.4.0)
Requires-Dist: dulwich (==0.24.1)
Requires-Dist: fastjsonschema (==2.21.2)
Requires-Dist: filelock (==3.19.1)
Requires-Dist: findpython (==0.7.0)
Requires-Dist: h11 (==0.16.0)
Requires-Dist: httpcore (==1.0.9)
Requires-Dist: httpx (==0.28.1)
Requires-Dist: idna (==3.10)
Requires-Dist: installer (==0.7.0)
Requires-Dist: jaraco-classes (==3.4.0)
Requires-Dist: jaraco-context (==6.0.1)
Requires-Dist: jaraco-functools (==4.3.0)
Requires-Dist: keyring (==25.6.0)
Requires-Dist: more-itertools (==10.8.0)
Requires-Dist: msgpack (==1.1.1)
Requires-Dist: packaging (==25.0)
Requires-Dist: pbs-installer (==2025.9.2)
Requires-Dist: pkginfo (==1.12.1.2)
Requires-Dist: platformdirs (==4.4.0)
Requires-Dist: poetry (==2.2.0)
Requires-Dist: poetry-core (==2.2.0)
Requires-Dist: pycparser (==2.23)
Requires-Dist: pyproject-hooks (==1.2.0)
Requires-Dist: rapidfuzz (==3.14.1)
Requires-Dist: requests (==2.32.5)
Requires-Dist: requests-toolbelt (==1.0.0)
Requires-Dist: scapy (==2.6.1)
Requires-Dist: setuptools (==80.9.0)
Requires-Dist: shellingham (==1.5.4)
Requires-Dist: sniffio (==1.3.1)
Requires-Dist: tomlkit (==0.13.3)
Requires-Dist: tqdm (==4.67.1)
Requires-Dist: trove-classifiers (==2025.9.11.17)
Requires-Dist: typing-extensions (==4.15.0)
Requires-Dist: urllib3 (==2.5.0)
Requires-Dist: virtualenv (==20.34.0)
Requires-Dist: xattr (==1.2.0)
Requires-Dist: zstandard (==0.25.0)
Project-URL: Homepage, https://github.com/mragusa/dns-traffic-analysis
